[{"title":"Rendering as NULL in XHP","description":"<p>There are some at Facebook who have argued against returning <code>null</code> when rendering an XHP element. In fact, it&rsquo;s actually against Facebook&rsquo;s standards now. Personally, I prefer to structure my code to return <code>null</code> in XHP, but there definitely are pros and cons. I&rsquo;ll cover the situations in which you might want to return <code>null</code> and what the alternatives could be, and then you can decide for yourself.</p>\n<p><!-- more --></p>\n<p>First, let me clarify that when I say returning <code>null</code>, I actually mean returning an empty <code>&lt;x:frag&gt;</code> element from your <code>:x:element</code>-extended class – basically meaning you don&rsquo;t want it to render into anything. So when would you return <code>null</code> from an XHP element? Well, often times it is when the element should only conditionally exist. Let&rsquo;s contrive a simple example.</p>\n<blockquote>\n<p><code>class :post:edit-link extends :x:element {<br/><br/>  a","link":"https://codebeforethehorse.tumblr.com/post/80212486413","owner":"Stefan Parker"},{"title":"Tutorial on Mallet in Python","description":null,"link":"https://radimrehurek.com/2014/03/tutorial-on-mallet-in-python/?utm_source=rss&utm_medium=rss&utm_campaign=tutorial-on-mallet-in-python","owner":"Radim Řehůřek"}]