[{"title":"Navigating themes in restaurant reviews with Word Mover’s Distance","description":null,"link":"https://tech.opentable.com/navigating-themes-in-restaurant-reviews-with-word-movers-distance/","owner":"OpenTable"},{"title":"Why We Hack","description":"<figure data-orig-width=\"780\" data-orig-height=\"454\" class=\"tmblr-full\"><img src=\"https://64.media.tumblr.com/48047d54d0edb6320b606e5a82e78c9f/tumblr_inline_nsw859vRIy1r950yn_540.png\" alt=\"image\" data-orig-width=\"780\" data-orig-height=\"454\"/></figure><p>One of the longest-running traditions at Wattpad is our Hack Fridays. <i>What is Hack Friday?</i> It&rsquo;s a monthly event to encourage creative problem solving in a free-form environment. Self-organized teams work on an idea to solve a problem and show others why their idea is awesome. That&rsquo;s the basic gist of it. When new people join Wattpad, a feedback I often get is how much they enjoy the experience and how much they look forward to it next month. Outsiders are often curious to know how it works and why we seemingly commit hundreds of hours each month to do things not directly related to our goals. Allen has <a href=\"http://blog.wattpad.com/2015/05/12/hackday-culture-at-wattpad/\">shared his insight</a> on <i>what we do</i>,","link":"https://engineering.wattpad.com/post/126422055407","owner":"Wattpad"}]