[{"title":"tota11y - an accessibility visualization toolkit","description":"","link":"http://engineering.khanacademy.org/posts/tota11y.htm","owner":"Khan Academy"},{"title":"Unicode woes in Javascript","description":"<p>At Mixmax, we send a lot of email. So we run into just about every unicode issue. This post describes a key learning about iterating strings in Javascript and why it's so often done wrong.</p>\n\n<p class=\"poet-read-more\"><a href=\"/blog/unicode-woes-in-javascript\" title=\"Read more of Unicode woes in Javascript\">Continue reading</a></p>","link":"https://mixmax.com/blog/unicode-woes-in-javascript","owner":"Mixmax"}]