[{"title":"Christmas in Vietnam: Mui Ne and Saigon","description":null,"link":"https://radimrehurek.com/2016/02/christmas-in-vietnam-mui-ne-and-saigon/?utm_source=rss&utm_medium=rss&utm_campaign=christmas-in-vietnam-mui-ne-and-saigon","owner":"Radim Řehůřek"},{"title":"Free objects - a generalized interpreter pattern","description":"In the GOF book, the interpreter pattern is probably one of the most poorly described patterns. The interpreter pattern basically consists…","link":"https://engineering.wingify.com//posts/Free-objects/","owner":"Wingify"},{"title":"The Problem with Customer Support","description":null,"link":"https://fullstack.info/the-problem-with-customer-support/","owner":"Ofer Zelig"}]