[{"title":"io_submit - The epoll alternative","description":"","link":"https://idea.popcount.org/2019-01-04-io_submit---the-epoll-alternative","owner":"Marek Majkowski"},{"title":"Memento mori","description":"One day you will be gone. What defines your legacy, is not the gadgets you had, but what impact you left behind. One day your name will be forgotten. But your legacy will live on. Your impact will live on in others, even if they don’t know your name. One day your words will be","link":"https://www.bjornjohansen.com/memento-mori","owner":"Bjørn Johansen"}]