[{"title":"How to hack the form? SQL Injection","description":"All programmers have read or at least heard about the methods to hack the website’s security. Or even faced this problem. A the same time, the creativity of people who want to break a website is endless, so all bottlenecks should be well secured. That’s why I would like to start a series of short […]","link":"http://piotrpasich.com/how-to-hack-the-form-sql-injection/?utm_source=rss&utm_medium=rss&utm_campaign=how-to-hack-the-form-sql-injection","owner":"Pony Foo"},{"title":"Receiving feedback as an intern at Khan Academy","description":"","link":"http://engineering.khanacademy.org/posts/receiving-feedback.htm","owner":"Just Eat"}]