[{"title":"Alert or ActionSheet style?","description":"","link":"https://up.smartrecruiters.com/alert-or-actionsheet-style-b0670796e8b7?source=rss----daef777a2064---4","owner":"Small Improvements"},{"title":"Determine If A Number Is Prime Using The Go Programming Language","description":"\n                    <p>Almost two years ago I wrote an article explaining how to <a href=\"https://www.thepolyglotdeveloper.com/2015/04/determine-if-a-number-is-prime-using-javascript/\">determine if a number is prime or not using JavaScript</a>. It turns out this article became more popular than I thought it would, and if I had to guess, it might be because it is a good computer science and overall interview question for new career developers.</p>\n<p>I thought it would make sense to revisit the post, but this time focus on accomplishing the task with the Go programming language instead of JavaScript.</p>\n                    \n                        <p>The post <a rel='nofollow' href='https://www.thepolyglotdeveloper.com/2016/12/determine-number-prime-using-golang/'>Determine If A Number Is Prime Using The Go Programming Language</a> appeared first on <a rel='nofollow' href='https://www.thepolyglotdeveloper.com'>The Polyglot Developer</a>.</p>\n                    \n                ","link":"https://www.thepolyglotdeveloper.com/2016/12/determine-number-prime-using-golang/","owner":"Nelson Elhage"},{"title":"Devoxx Belgium 2016","description":"","link":"https://up.smartrecruiters.com/devoxx-belgium-2016-d2283d177049?source=rss----daef777a2064---4","owner":"Small Improvements"},{"title":"How to Write an Engineering Blog Post","description":"<p>When we came up with the idea for the <a href=\"/blog/mixmax-eng-advent-2016\">Mixmax Advent Calendar</a>, some team members worried they wouldn&#39;t have anything to write. In response, we came up with some strategies that everyone could use to write a post. And in the spirit of giving <a href=\"/blog/mixmax-eng-advent-2016\">with which we began</a> the series, we’ll finish by sharing these strategies with you.</p>\n<p class=\"poet-read-more\"><a href=\"/blog/how-to-write-an-engineering-blog-post\" title=\"Read more of How to Write an Engineering Blog Post\">Continue reading</a></p>","link":"https://mixmax.com/blog/how-to-write-an-engineering-blog-post","owner":"Microsoft Python Engineering"}]