[{"title":"A Quick Trick to Make a Java Stream Construction Lazy","description":"One of the Stream APIs greatest features is its laziness. The whole pipeline is constructed lazily, stored as a set of instructions, akin to a SQL execution plan. Only when we invoke a terminal operation, the pipeline is started. It is still lazy, meaning that some operations may be short circuited. Some third party libraries … ","link":"https://blog.jooq.org/2019/09/30/a-quick-trick-to-make-a-java-stream-construction-lazy/","owner":"jOOQ"},{"title":"How to Make Good Code Reviews Better","description":null,"link":"https://stackoverflow.blog/2019/09/30/how-to-make-good-code-reviews-better/","owner":"Stack Overflow"},{"title":"TCP Puzzles 1-2","description":"","link":"https://idea.popcount.org/2019-09-30-tcp-puzzles-1-2","owner":"Marek Majkowski"},{"title":"The Ghost in the Hashes","description":"","link":"https://medium.engineering/the-ghost-in-the-hashes-55ef1e3a86ef?source=rss----2817475205d3---4","owner":"Medium"}]