[{"title":"Optimising React Native APK Size","description":"","link":"https://medium.com/engineering-housing/optimising-react-native-apk-size-c88ef39ab7a0?source=rss----3a69e32e2594---4","owner":"Hostinger"},{"title":"TPDP Episode #29: Asynchronous JavaScript Development","description":"\n                    <p>The latest episode of The Polyglot Developer Podcast has just published, this time focusing on the use of callbacks, promises, and async / await, in JavaScript.</p>\n<p>This episode titled, <strong>Asynchronous JavaScript Development</strong>, is the twenty-ninth episode to appear on the show and it features <a href=\"https://unicorn-utterances.com/\">Corbin Crutchley</a>, an expert JavaScript developer and open source maintainer.</p>\n<p>If you&rsquo;ve ever struggled with wrapping your head around working with remote resources or blocking tasks in JavaScript, this episode should clear things up.</p>\n                    \n                        <p>The post <a rel='nofollow' href='https://www.thepolyglotdeveloper.com/2019/07/tpdp-e29-asynchronous-javascript-development/'>TPDP Episode #29: Asynchronous JavaScript Development</a> appeared first on <a rel='nofollow' href='https://www.thepolyglotdeveloper.com'>The Polyglot Developer</a>.</p>\n                    \n       ","link":"https://www.thepolyglotdeveloper.com/2019/07/tpdp-e29-asynchronous-javascript-development/","owner":"Nelson Elhage"}]