[{"title":"[SAT] UNSAT core","description":"[SAT] UNSAT core","link":"https://yurichev.com/news/20200801_MUS/","owner":"Dennis Felsing"},{"title":"Create a RESTful API using Node and Express with MySQL Database","description":"<div class=\"bigInt\" itemprop=\"description\">Node Express web framework is a best solution to create RESTful APIs in quick time. Previously we published some concepts with different technologies like PHP and Java.  This article will explain to you a more simple way to use external plugins to enrich your project APIs.  Here you will find to create GET and POST requests with request payload validations to protect the endpoints.  </div><br><div class=\"cen\"><img alt=\"Node Express MySQL RESTful\" class=\"sri650\" itemprop=\"image\" src=\"https://github.com/srinivastamada/9lessonsImages/blob/master/node-mysql/node-mysql-express.png?raw=true\"></div><br><a href=\"http://www.9lessons.info/2020/04/create-restful-api-using-node-and.html#more\"></a><div class=\"feedflare\">\r\n<a href=\"http://feeds.feedburner.com/~ff/9lesson?a=KcpY6EOTl3Y:eRM6bOpoqdM:yIl2AUoC8zA\"><img src=\"http://feeds.feedburner.com/~ff/9lesson?d=yIl2AUoC8zA\" border=\"0\"></img></a> <a href=\"http://feeds.feedburner.com/~ff/9lesson?a=KcpY6EOTl3Y:","link":"http://feedproxy.google.com/~r/9lesson/~3/KcpY6EOTl3Y/create-restful-api-using-node-and.html","owner":"Simon Reimler"}]